pychoreo/__init__.py
pychoreo/__version__.py
pychoreo/cartesian_planner/__init__.py
pychoreo/cartesian_planner/dag_search.py
pychoreo/cartesian_planner/ladder_graph.py
pychoreo/cartesian_planner/ladder_graph_interface.py
pychoreo/cartesian_planner/postprocessing.py
pychoreo/cartesian_planner/sparse_ladder_graph.py
pychoreo/process_model/__init__.py
pychoreo/process_model/cartesian_process.py
pychoreo/process_model/gen_fn.py
pychoreo/process_model/trajectory.py
pychoreo/sequence_planner/__init__.py
pychoreo/sequence_planner/assembly_csp.py
pychoreo/sequence_planner/csp.py
pychoreo/sequence_planner/csp_utils.py
pychoreo/sequence_planner/sequence_utils.py
pychoreo/utils/__init__.py
pychoreo/utils/debug_utils.py
pychoreo/utils/general_utils.py
pychoreo/utils/parsing_utils.py
pychoreo/utils/stream_utils.py
pychoreo/utils/convex_decomp/README.md
pychoreo/utils/convex_decomp/__init__.py
pychoreo/utils/convex_decomp/run.py
pychoreo_examples/__init__.py
pychoreo_examples/data/assembly_instances/.git
pychoreo_examples/data/assembly_instances/.gitignore
pychoreo_examples/data/assembly_instances/README.md
pychoreo_examples/data/assembly_instances/extrusion/.extrusion_exp_L75.0.json.un~
pychoreo_examples/data/assembly_instances/extrusion/C_shape.json
pychoreo_examples/data/assembly_instances/extrusion/DJMM_bridge.json
pychoreo_examples/data/assembly_instances/extrusion/README.md
pychoreo_examples/data/assembly_instances/extrusion/bunny_full_quad.json
pychoreo_examples/data/assembly_instances/extrusion/bunny_full_tri.json
pychoreo_examples/data/assembly_instances/extrusion/bunny_full_tri_dense.json
pychoreo_examples/data/assembly_instances/extrusion/compas_fea_beam_tree.json
pychoreo_examples/data/assembly_instances/extrusion/compas_fea_beam_tree_M.json
pychoreo_examples/data/assembly_instances/extrusion/compas_fea_beam_tree_S.json
pychoreo_examples/data/assembly_instances/extrusion/compas_fea_truss_frame.json
pychoreo_examples/data/assembly_instances/extrusion/david.json
pychoreo-0.3.0.dist-info/AUTHORS.rst
pychoreo-0.3.0.dist-info/LICENSE
pychoreo-0.3.0.dist-info/METADATA
pychoreo-0.3.0.dist-info/WHEEL
pychoreo-0.3.0.dist-info/top_level.txt
pychoreo-0.3.0.dist-info/RECORD
