Metadata-Version: 2.1
Name: pychoreo
Version: 0.3.0
Summary: sequence and motion planning for robotic spatial extrusion
Home-page: https://github.com/yijiangh/pychoreo
Author: Yijiang Huang
Author-email: yijiangh@mit.edu
License: MIT license
Keywords: robotic fabrication,digital fabrication,architecture,robotics,ros
Platform: UNKNOWN
Classifier: Development Status :: 3 - Alpha
Classifier: Intended Audience :: Developers
Classifier: Intended Audience :: Science/Research
Classifier: License :: OSI Approved :: MIT License
Classifier: Operating System :: Unix
Classifier: Operating System :: POSIX
Classifier: Operating System :: Microsoft :: Windows
Classifier: Programming Language :: Python
Classifier: Programming Language :: Python :: 2.7
Classifier: Programming Language :: Python :: 3
Classifier: Programming Language :: Python :: 3.3
Classifier: Programming Language :: Python :: 3.4
Classifier: Programming Language :: Python :: 3.5
Classifier: Programming Language :: Python :: 3.6
Classifier: Programming Language :: Python :: Implementation :: CPython
Classifier: Topic :: Scientific/Engineering
Requires-Dist: numpy
Requires-Dist: pybullet
Requires-Dist: pybullet-planning
Requires-Dist: ikfast-pybind
Requires-Dist: compas-fab
